{
  "human_name": "Demi Osaki",
  "email": "Demi.Osaki@ennead.com",
  "bio": "",
  "phone": "1-213-787-6612",
  "mobile": "1-213-787-6612",
  "office_location": "",
  "profile_url": "https://ei.ennead.com/employee/A23D36C3-03CF-451A-AA57-49DA76859895/demi-osaki",
  "image_url": "https://ei.ennead.com/api/image/801d12f0-d09d-4858-9c4e-f4c9764b4fb1/preview?size=150w150h&version=0",
  "image_local_path": null,
  "position": "",
  "department": "",
  "years_with_firm": null,
  "seat_assignment": null,
  "computer": "You need to enable JavaScript to use Synthesis.\n    Skip to Main ContentHelp?HomeOfficeCommunitiesToolboxDesign TechnologyWatercoolerLibrariesLeadershipSearch ei > Employee Directory > Demi OsakiDemi OsakiMarketing CoordinatorThe BasicsYears With Firm0EducationInstitutionDegreeSpecialtyUniversity of CaliforniaUndergraduateGraphic DesignOrange Coast CollegeAssociatesStudio ArtsContact InfoEmailDemi.Osaki@ennead.comPhone1-213-787-6612TeamsRecent PostsCopy link to thisLA office summer outing at Dodger Stadium!Like this36Comment·Aug 7·",
  "memberships": [],
  "education": [],
  "licenses": [],
  "projects": [],
  "recent_posts": [],
  "teams_url": "https://teams.microsoft.com/l/chat/0/0?users=Demi.Osaki@ennead.com",
  "linkedin_url": null,
  "website_url": null,
  "scraped_at": "2025-09-15T18:34:31.786666",
  "profile_id": null
}